geojson/__init__.py
geojson/_version.py
geojson/base.py
geojson/codec.py
geojson/crs.py
geojson/examples.py
geojson/factory.py
geojson/feature.py
geojson/geometry.py
geojson/mapping.py
geojson/utils.py
geojson-2.4.1.dist-info/LICENSE.rst
geojson-2.4.1.dist-info/METADATA
geojson-2.4.1.dist-info/WHEEL
geojson-2.4.1.dist-info/top_level.txt
geojson-2.4.1.dist-info/RECORD
