Metadata-Version: 1.2
Name: geojson
Version: 2.4.1
Summary: Python bindings and utilities for GeoJSON
Home-page: https://github.com/frewsxcv/python-geojson
Author: Sean Gillies
Author-email: sgillies@frii.com
Maintainer: Corey Farwell
Maintainer-email: coreyf@rwell.org
License: BSD
Keywords: gis geography json
Platform: UNKNOWN
Classifier: Development Status :: 5 - Production/Stable
Classifier: Intended Audience :: Developers
Classifier: Intended Audience :: Science/Research
Classifier: License :: OSI Approved :: BSD License
Classifier: Operating System :: OS Independent
Classifier: Programming Language :: Python
Classifier: Programming Language :: Python :: 2
Classifier: Programming Language :: Python :: 2.7
Classifier: Programming Language :: Python :: 3
Classifier: Programming Language :: Python :: 3.3
Classifier: Programming Language :: Python :: 3.4
Classifier: Programming Language :: Python :: 3.5
Classifier: Programming Language :: Python :: 3.6
Classifier: Topic :: Scientific/Engineering :: GIS
